langflow_client/__init__.py
langflow_client/client.py
langflow_client/constants.py
langflow_client/exceptions.py
langflow_client/flow.py
langflow_client/models.py
langflow_client/py.typed
langflow_python_client-1.0.0.dist-info/licenses/LICENSE
langflow_python_client-1.0.0.dist-info/METADATA
langflow_python_client-1.0.0.dist-info/WHEEL
langflow_python_client-1.0.0.dist-info/top_level.txt
langflow_python_client-1.0.0.dist-info/RECORD
