Metadata-Version: 2.4
Name: langflow-python-client
Version: 1.0.0
Summary: Async Python client library for interacting with Langflow API servers
Author-email: Adrián Noya Carro <anoya@ikerlan.es>
License: MIT
Project-URL: Repository, https://github.com/MattinAI/langflow-client
Project-URL: Homepage, https://github.com/MattinAI/langflow-client
Project-URL: Issues, https://github.com/MattinAI/langflow-client/issues
Keywords: langflow,client,api,ai,llm,async,python
Classifier: Development Status :: 5 - Production/Stable
Classifier: Intended Audience :: Developers
Classifier: License :: OSI Approved :: MIT License
Classifier: Operating System :: OS Independent
Classifier: Programming Language :: Python :: 3.10
Classifier: Programming Language :: Python :: 3.11
Classifier: Programming Language :: Python :: 3.12
Classifier: Programming Language :: Python :: 3.13
Classifier: Topic :: Software Development :: Libraries :: Python Modules
Classifier: Topic :: Internet :: WWW/HTTP :: HTTP Servers
Classifier: Topic :: Scientific/Engineering :: Artificial Intelligence
Classifier: Typing :: Typed
Requires-Python: >=3.10
License-File: LICENSE
Requires-Dist: httpx>=0.24.0
Requires-Dist: pydantic>=2.11.0
Requires-Dist: aiofiles>=24.1.0
Provides-Extra: dev
Requires-Dist: pytest>=8.3.0; extra == "dev"
Requires-Dist: pytest-asyncio>=0.24.0; extra == "dev"
Requires-Dist: pytest-httpx>=0.32.0; extra == "dev"
Requires-Dist: pytest-cov>=6.2.0; extra == "dev"
Requires-Dist: black>=24.0.0; extra == "dev"
Requires-Dist: isort>=5.13.0; extra == "dev"
Requires-Dist: ruff>=0.6.0; extra == "dev"
Requires-Dist: mypy>=1.11.0; extra == "dev"
Requires-Dist: coverage[toml]>=7.6.0; extra == "dev"
Provides-Extra: docs
Requires-Dist: sphinx>=8.0.0; extra == "docs"
Requires-Dist: sphinx-rtd-theme>=3.0.0; extra == "docs"
Requires-Dist: myst-parser>=4.0.0; extra == "docs"
Dynamic: license-file
